allenlib/__init__.py
allenlib/computer_os.py
allenlib/message.py
allenlib/print_load.py
allenlib/printfun.py
allenlib/raise.py
allenlib/readini.py
allenlib/simplepygame.py
allenlib/speak.py
allenlib-6.0.1.dist-info/METADATA
allenlib-6.0.1.dist-info/WHEEL
allenlib-6.0.1.dist-info/top_level.txt
allenlib-6.0.1.dist-info/RECORD
