Metadata-Version: 2.1
Name: allenlib
Version: 6.0.1
Summary: allenlib
Home-page: UNKNOWN
Author: 刘雨桐
Author-email: UNKNOWN
Maintainer: 刘雨桐
Maintainer-email: UNKNOWN
License: BSD License
Platform: all
Classifier: Development Status :: 4 - Beta
Classifier: Operating System :: OS Independent
Classifier: Intended Audience :: Developers
Classifier: License :: OSI Approved :: BSD License
Classifier: Programming Language :: Python :: 3
Classifier: Topic :: Software Development :: Libraries
Requires-Dist: requests
Requires-Dist: pygame
